{
  "entrypoints": [
    "main"
  ],
  "origins": {
    "237": [
      76,
      237
    ],
    "436": [
      436
    ],
    "437": [
      583,
      437
    ],
    "17896441": [
      76,
      869,
      401
    ],
    "main": [
      354,
      869,
      792
    ],
    "runtime~main": [
      792,
      869,
      354
    ],
    "0cccfd7d": [
      177
    ],
    "1df93b7f": [
      437,
      583
    ],
    "1f391b9e": [
      76,
      869,
      61
    ],
    "4c678320": [
      76,
      664
    ],
    "5281b7a2": [
      76,
      443
    ],
    "5e95c892": [
      647
    ],
    "a7456010": [
      235
    ],
    "a7bd4aaa": [
      98
    ],
    "a94703ab": [
      76,
      869,
      48
    ],
    "aba21aa0": [
      742
    ],
    "styles": [
      48,
      61,
      76,
      354,
      401,
      792,
      869
    ],
    "common": [
      48,
      61,
      237,
      401,
      443,
      664,
      869,
      76
    ]
  },
  "assets": {
    "48": {
      "js": [
        {
          "file": "assets/js/a94703ab.03978a65.js",
          "hash": "0f21ebc14ed30631",
          "publicPath": "/DesktopPet/assets/js/a94703ab.03978a65.js"
        }
      ]
    },
    "61": {
      "js": [
        {
          "file": "assets/js/1f391b9e.e00271c2.js",
          "hash": "ce9e3d60625bd618",
          "publicPath": "/DesktopPet/assets/js/1f391b9e.e00271c2.js"
        }
      ]
    },
    "76": {
      "js": [
        {
          "file": "assets/js/common.d83383e0.js",
          "hash": "f9faf616289cc103",
          "publicPath": "/DesktopPet/assets/js/common.d83383e0.js"
        }
      ]
    },
    "98": {
      "js": [
        {
          "file": "assets/js/a7bd4aaa.0b489c09.js",
          "hash": "985f1011acf4142a",
          "publicPath": "/DesktopPet/assets/js/a7bd4aaa.0b489c09.js"
        }
      ]
    },
    "177": {
      "js": [
        {
          "file": "assets/js/0cccfd7d.bd4ee9cd.js",
          "hash": "9761aeef39181fea",
          "publicPath": "/DesktopPet/assets/js/0cccfd7d.bd4ee9cd.js"
        }
      ]
    },
    "235": {
      "js": [
        {
          "file": "assets/js/a7456010.7bc947ef.js",
          "hash": "7346e188d57421f7",
          "publicPath": "/DesktopPet/assets/js/a7456010.7bc947ef.js"
        }
      ]
    },
    "237": {
      "js": [
        {
          "file": "assets/js/237.149bc9f5.js",
          "hash": "fb2a0ecfecd9272b",
          "publicPath": "/DesktopPet/assets/js/237.149bc9f5.js"
        }
      ]
    },
    "354": {
      "js": [
        {
          "file": "assets/js/runtime~main.69211bd4.js",
          "hash": "0c5bcc3c5c11bf69",
          "publicPath": "/DesktopPet/assets/js/runtime~main.69211bd4.js"
        }
      ]
    },
    "401": {
      "js": [
        {
          "file": "assets/js/17896441.1f12c7d7.js",
          "hash": "08d2504fb16ee000",
          "publicPath": "/DesktopPet/assets/js/17896441.1f12c7d7.js"
        }
      ]
    },
    "436": {
      "js": [
        {
          "file": "assets/js/436.058a0146.js",
          "hash": "5b39655fe4f0b010",
          "publicPath": "/DesktopPet/assets/js/436.058a0146.js"
        }
      ]
    },
    "437": {
      "js": [
        {
          "file": "assets/js/437.d397dc29.js",
          "hash": "0fc0348a7fae0920",
          "publicPath": "/DesktopPet/assets/js/437.d397dc29.js"
        }
      ]
    },
    "443": {
      "js": [
        {
          "file": "assets/js/5281b7a2.c4fad13e.js",
          "hash": "84fb9f2e3e512bf6",
          "publicPath": "/DesktopPet/assets/js/5281b7a2.c4fad13e.js"
        }
      ]
    },
    "583": {
      "js": [
        {
          "file": "assets/js/1df93b7f.01a02f51.js",
          "hash": "0acc592a25131c86",
          "publicPath": "/DesktopPet/assets/js/1df93b7f.01a02f51.js"
        }
      ]
    },
    "647": {
      "js": [
        {
          "file": "assets/js/5e95c892.9503a094.js",
          "hash": "49941d4d76ee5eee",
          "publicPath": "/DesktopPet/assets/js/5e95c892.9503a094.js"
        }
      ]
    },
    "664": {
      "js": [
        {
          "file": "assets/js/4c678320.5a3aede7.js",
          "hash": "ee46e81578d920a6",
          "publicPath": "/DesktopPet/assets/js/4c678320.5a3aede7.js"
        }
      ]
    },
    "742": {
      "js": [
        {
          "file": "assets/js/aba21aa0.6c061b4f.js",
          "hash": "885be4b2d767f8aa",
          "publicPath": "/DesktopPet/assets/js/aba21aa0.6c061b4f.js"
        }
      ]
    },
    "792": {
      "js": [
        {
          "file": "assets/js/main.7bbc3bb2.js",
          "hash": "62b143c9b8245450",
          "publicPath": "/DesktopPet/assets/js/main.7bbc3bb2.js"
        }
      ]
    },
    "869": {
      "css": [
        {
          "file": "assets/css/styles.83777dc9.css",
          "hash": "7b3a8f6eb98a0318",
          "publicPath": "/DesktopPet/assets/css/styles.83777dc9.css"
        }
      ]
    }
  }
}